Metadata-Version: 2.1
Name: vernierpygatt
Version: 3.2.0
Summary: Python Bluetooth LE (Low Energy) and GATT Library
Home-page: https://github.com/VernierST/pygatt
Author: Chris Peplin <github@rhubarbtech.com>, Vernier Software and Technology
Author-email: info@vernier.com
License: Apache 2.0 and MIT
Platform: UNKNOWN
Classifier: Intended Audience :: Developers
Classifier: License :: OSI Approved :: Apache Software License
Classifier: License :: OSI Approved :: MIT License
Classifier: Programming Language :: Python
Classifier: Programming Language :: Python :: 2.7
Classifier: Programming Language :: Python :: 3
Requires-Dist: pyserial
Requires-Dist: enum-compat
Provides-Extra: gatttool
Requires-Dist: pexpect; extra == 'gatttool'
